odoo/addons/stock_picking_product_link/README.rst
odoo/addons/stock_picking_product_link/__init__.py
odoo/addons/stock_picking_product_link/__manifest__.py
odoo/addons/stock_picking_product_link/i18n/es.po
odoo/addons/stock_picking_product_link/i18n/it.po
odoo/addons/stock_picking_product_link/i18n/stock_picking_product_link.pot
odoo/addons/stock_picking_product_link/models/__init__.py
odoo/addons/stock_picking_product_link/models/stock_picking.py
odoo/addons/stock_picking_product_link/readme/CONTRIBUTORS.rst
odoo/addons/stock_picking_product_link/readme/CREDITS.rst
odoo/addons/stock_picking_product_link/readme/DESCRIPTION.rst
odoo/addons/stock_picking_product_link/static/description/icon.png
odoo/addons/stock_picking_product_link/static/description/index.html
odoo/addons/stock_picking_product_link/tests/__init__.py
odoo/addons/stock_picking_product_link/tests/test_stock_picking_product_link.py
odoo/addons/stock_picking_product_link/views/stock_picking_views.xml
odoo_addon_stock_picking_product_link-16.0.1.0.0.5.dist-info/METADATA
odoo_addon_stock_picking_product_link-16.0.1.0.0.5.dist-info/WHEEL
odoo_addon_stock_picking_product_link-16.0.1.0.0.5.dist-info/top_level.txt
odoo_addon_stock_picking_product_link-16.0.1.0.0.5.dist-info/RECORD
