Metadata-Version: 2.1
Name: odoo-addon-stock-picking-product-link
Version: 16.0.1.0.0.5
Summary: Adds a "Product" smart button on stock pickings.
Home-page: https://github.com/OCA/stock-logistics-workflow
Author: Odoo Community Association (OCA), Coop IT Easy SC
Author-email: support@odoo-community.org
License: AGPL-3
Platform: UNKNOWN
Classifier: Programming Language :: Python
Classifier: Framework :: Odoo
Classifier: Framework :: Odoo :: 16.0
Classifier: License :: OSI Approved :: GNU Affero General Public License v3
Requires-Python: >=3.10
Requires-Dist: odoo <16.1dev,>=16.0a
